README.md
setup.py
pulumi_volcengine/__init__.py
pulumi_volcengine/_inputs.py
pulumi_volcengine/_utilities.py
pulumi_volcengine/provider.py
pulumi_volcengine/pulumi-plugin.json
pulumi_volcengine/py.typed
pulumi_volcengine.egg-info/PKG-INFO
pulumi_volcengine.egg-info/SOURCES.txt
pulumi_volcengine.egg-info/dependency_links.txt
pulumi_volcengine.egg-info/not-zip-safe
pulumi_volcengine.egg-info/requires.txt
pulumi_volcengine.egg-info/top_level.txt
pulumi_volcengine/alb/__init__.py
pulumi_volcengine/alb/_inputs.py
pulumi_volcengine/alb/acl.py
pulumi_volcengine/alb/acls.py
pulumi_volcengine/alb/alb.py
pulumi_volcengine/alb/albs.py
pulumi_volcengine/alb/ca_certificate.py
pulumi_volcengine/alb/ca_certificates.py
pulumi_volcengine/alb/certificate.py
pulumi_volcengine/alb/certificates.py
pulumi_volcengine/alb/customized_cfg.py
pulumi_volcengine/alb/customized_cfgs.py
pulumi_volcengine/alb/get_acls.py
pulumi_volcengine/alb/get_albs.py
pulumi_volcengine/alb/get_ca_certificates.py
pulumi_volcengine/alb/get_certificates.py
pulumi_volcengine/alb/get_customized_cfgs.py
pulumi_volcengine/alb/get_health_check_templates.py
pulumi_volcengine/alb/get_listener_domain_extensions.py
pulumi_volcengine/alb/get_listeners.py
pulumi_volcengine/alb/get_rules.py
pulumi_volcengine/alb/get_server_group_servers.py
pulumi_volcengine/alb/get_server_groups.py
pulumi_volcengine/alb/get_zones.py
pulumi_volcengine/alb/health_check_template.py
pulumi_volcengine/alb/health_check_templates.py
pulumi_volcengine/alb/listener.py
pulumi_volcengine/alb/listener_domain_extension.py
pulumi_volcengine/alb/listener_domain_extensions.py
pulumi_volcengine/alb/listeners.py
pulumi_volcengine/alb/outputs.py
pulumi_volcengine/alb/rule.py
pulumi_volcengine/alb/rules.py
pulumi_volcengine/alb/server_group.py
pulumi_volcengine/alb/server_group_server.py
pulumi_volcengine/alb/server_group_servers.py
pulumi_volcengine/alb/server_groups.py
pulumi_volcengine/alb/zones.py
pulumi_volcengine/apig/__init__.py
pulumi_volcengine/apig/_inputs.py
pulumi_volcengine/apig/apig_custom_domain.py
pulumi_volcengine/apig/apig_gateway.py
pulumi_volcengine/apig/apig_gateway_service.py
pulumi_volcengine/apig/apig_route.py
pulumi_volcengine/apig/apig_upstream.py
