Metadata-Version: 2.4
Name: pulumi_volcengine
Version: 0.0.41
Summary: A Pulumi package for creating and managing volcengine cloud resources.
Home-page: https://volcengine.com
License: Apache-2.0
Project-URL: Repository, https://github.com/volcengine/pulumi-volcengine
Keywords: pulumi volcengine category/cloud
Requires-Python: >=3.8
Requires-Dist: parver>=0.2.1
Requires-Dist: pulumi<4.0.0,>=3.0.0
Requires-Dist: semver>=2.8.1
Dynamic: description
Dynamic: description-content-type
Dynamic: home-page
Dynamic: keywords
Dynamic: license
Dynamic: project-url
Dynamic: requires-dist
Dynamic: requires-python
Dynamic: summary
